django_tidings-2.0.1.dist-info/DESCRIPTION.rst
django_tidings-2.0.1.dist-info/METADATA
django_tidings-2.0.1.dist-info/RECORD
django_tidings-2.0.1.dist-info/WHEEL
django_tidings-2.0.1.dist-info/metadata.json
django_tidings-2.0.1.dist-info/top_level.txt
tidings/__init__.py
tidings/admin.py
tidings/compat.py
tidings/events.py
tidings/models.py
tidings/tasks.py
tidings/urls.py
tidings/utils.py
tidings/views.py
tidings/migrations/0001_initial.py
tidings/migrations/0002_update_email_size.py
tidings/migrations/__init__.py
tidings/templates/base.html
tidings/templates/tidings/base.html
tidings/templates/tidings/unsubscribe.html
tidings/templates/tidings/unsubscribe_error.html
tidings/templates/tidings/unsubscribe_success.html
tidings/templates/tidings/email/unsubscribe.ltxt
tidings/templatetags/__init__.py
tidings/templatetags/unsubscribe_instructions.py
